{
  "compilerOptions": {
    "module": "commonjs",
    "moduleResolution": "node",
    "target": "ES2021",
    "lib": ["ES2021", "DOM"],
    "declaration": true,
    "removeComments": true,
    "emitDecoratorMetadata": true,
    "experimentalDecorators": true,
    "allowSyntheticDefaultImports": true,
    "esModuleInterop": true,
    "strict": true,
    "strictNullChecks": true,
    "noImplicitAny": true,
    "strictBindCallApply": true,
    "forceConsistentCasingInFileNames": true,
    "noFallthroughCasesInSwitch": true,
    "incremental": true,
    "sourceMap": true,
    "inlineSources": true,
    "outDir": "./dist",
    "baseUrl": "./",
    "skipLibCheck": true,
    "types": ["node"]
  }
}
